princurve/__init__.py
princurve/glob.py
princurve/local.py
princurve-0.0.1.dist-info/LICENSE
princurve-0.0.1.dist-info/METADATA
princurve-0.0.1.dist-info/WHEEL
princurve-0.0.1.dist-info/top_level.txt
princurve-0.0.1.dist-info/RECORD
