Metadata-Version: 2.1
Name: princurve
Version: 0.0.1
Summary: A package for fitting principal curves in Python
Home-page: https://github.com/wangzichenbioinformatics/princurve
Author: https://github.com/wangzichenbioinformatics
Author-email: wch_bioinformatics@163.com
License: MIT
Platform: UNKNOWN
License-File: LICENSE
Requires-Dist: numpy
Requires-Dist: matplotlib
Requires-Dist: scipy
Requires-Dist: keras
Requires-Dist: tensorflow
